nbdesk/tracing.py
nbdesk/widgets/__init__.py
nbdesk/widgets/output.py
nbdesk/widgets/results.py
nbdesk/widgets/worker.py
nbdesk-0.0.1.dist-info/METADATA
nbdesk-0.0.1.dist-info/WHEEL
nbdesk-0.0.1.dist-info/licenses/LICENSE.txt
nbdesk-0.0.1.dist-info/RECORD
